emojify/__init__.py
emojify/core.py
emojify/emoji_map.py
emojify_asid-0.1.3.dist-info/METADATA
emojify_asid-0.1.3.dist-info/WHEEL
emojify_asid-0.1.3.dist-info/top_level.txt
emojify_asid-0.1.3.dist-info/RECORD
